cluecode
commoncode
extractcode
formattedcode
licensedcode
packagedcode
plugincode
scancode
scancode_config
summarycode
textcode
typecode
