Metadata-Version: 2.1
Name: scancode-toolkit
Version: 2.9.4
Summary: ScanCode is a tool to scan code for license, copyright, package and their documented dependencies and other interesting facts.
Home-page: https://github.com/nexB/scancode-toolkit
Author: ScanCode
Author-email: info@aboutcode.org
License: Apache-2.0 with ScanCode acknowledgment and CC0-1.0 and others
Keywords: open source,scan,license,package,dependency,copyright,filetype,author,extract,licensing
Platform: UNKNOWN
Classifier: Development Status :: 5 - Production/Stable
Classifier: Intended Audience :: Developers
Classifier: License :: OSI Approved :: Apache Software License
Classifier: License :: CC0 1.0 Universal (CC0 1.0) Public Domain Dedication
Classifier: Programming Language :: Python
Classifier: Programming Language :: Python :: 2.7
Classifier: Topic :: Utilities
Requires-Dist: nltk (<4.0,>=3.2)
Requires-Dist: publicsuffix2
Requires-Dist: py2-ipaddress (<3.5,>=2.0)
Requires-Dist: url (<0.1.6,>=0.1.4)
Requires-Dist: fingerprints (==0.5.4)
Requires-Dist: patch (<1.20,>=1.15)
Requires-Dist: bz2file (>=0.98)
Requires-Dist: extractcode-libarchive
Requires-Dist: extractcode-7z
Requires-Dist: backports.os (==0.1.1)
Requires-Dist: future (==0.16.0)
Requires-Dist: text-unidecode (<2.0,>=1.0)
Requires-Dist: bitarray (<1.0.0,>=0.8.1)
Requires-Dist: intbitset (<3.0,>=2.3.0)
Requires-Dist: boolean.py (<4.0,>=3.5)
Requires-Dist: license-expression (<1.0,>=0.99)
Requires-Dist: pyahocorasick (<1.2,>=1.1)
Requires-Dist: PyYAML (<4.0,>=3.0)
Requires-Dist: lxml (<5.0.0,>=4.0.0)
Requires-Dist: Beautifulsoup4 (<5.0.0,>=4.0.0)
Requires-Dist: html5lib
Requires-Dist: six
Requires-Dist: pdfminer.six (>=20170720)
Requires-Dist: pycryptodome (>=3.4)
Requires-Dist: binaryornot (>=0.4.0)
Requires-Dist: chardet (<4.0.0,>=3.0.0)
Requires-Dist: pygments (<2.3,>=2.2.0)
Requires-Dist: typecode-libmagic
Requires-Dist: pefile (>=2018.8.8)
Requires-Dist: pymaven-patch (>=0.2.4)
Requires-Dist: requests (<3.0.0,>=2.7.0)
Requires-Dist: packageurl-python (>=0.5.0)
Requires-Dist: xmltodict (>=0.11.0)
Requires-Dist: click (<7.0.0,>=6.0.0)
Requires-Dist: colorama (>=0.3.9)
Requires-Dist: pluggy (<1.0,>=0.4.0)
Requires-Dist: attrs (<19.0,>=17.4)
Requires-Dist: cattrs
Requires-Dist: typing (<3.7,>=3.6)
Requires-Dist: jinja2 (<3.0.0,>=2.7.0)
Requires-Dist: MarkupSafe (>=0.23)
Requires-Dist: simplejson
Requires-Dist: spdx-tools (>=0.5.4)
Requires-Dist: unicodecsv
Requires-Dist: psutil (<6.0.0,>=5.0.0)
Requires-Dist: yg.lockfile (<3.0.0,>=2.0.1)
Requires-Dist: contextlib2
Requires-Dist: pytz
Requires-Dist: tempora
Requires-Dist: jaraco.timing
Requires-Dist: zc.lockfile (<2.0.1,>=1.0.0)
